{
  "status": "researched",
  "summary": "Analyzed README.md for Task 662: identified Quick Start section (lines 41-83) for removal, found ~60% content duplication with system-overview.md requiring consolidation, verified all file paths are accurate, and documented recommendations for restructuring as navigation hub.",
  "artifacts": [
    {
      "type": "research",
      "path": "specs/662_consolidate_update_docs_readme/reports/research-001.md",
      "summary": "Research report with detailed analysis of README.md, consolidation opportunities with system-overview.md, and specific recommendations for rewrite"
    }
  ],
  "completion_data": null
}
