{
  "status": "researched",
  "summary": "Identified 4 key modifications needed in skill-learn/SKILL.md: (1) reverse task creation order when NOTE: tags exist, (2) add dependency from fix-it to learn-it task, (3) update learn-it description to include NOTE: -> FIX: replacement instruction, (4) update documentation. Clear division of labor: learn-it handles context updates and tag conversion, fix-it handles file-local code changes.",
  "artifacts": [
    {
      "path": "specs/649_improve_learn_note_tag_dependency_handling/reports/research-001.md",
      "type": "research",
      "summary": "Research report documenting current /learn implementation, task dependency schema, and 4-phase modification approach for NOTE: tag dependency handling"
    }
  ],
  "next_steps": "Run /plan 649 to create implementation plan",
  "metadata": {
    "session_id": "sess_1768941822_3ef648",
    "agent_type": "general-research-agent",
    "duration_seconds": 180,
    "delegation_depth": 1,
    "delegation_path": ["orchestrator", "research", "skill-researcher"],
    "findings_count": 5
  }
}
