{
  "status": "planned",
  "summary": "Plan created for task 990",
  "artifacts": [
    {
      "type": "plan",
      "path": "specs/990_representation_theorem_duration_design/plans/01_parametric-duration-architecture.md",
      "summary": "5-phase plan to consolidate on D-parametric architecture: update ROAD_MAP.md strategy, add Lean documentation to ParametricRepresentation.lean and DFromCantor.lean clarifying primary/auxiliary roles, update BaseCompleteness.lean docs, and create architecture decision summary"
    }
  ],
  "metadata": {
    "phase_count": 5,
    "estimated_hours": 6.0,
    "session_id": "sess_1773785109_09fa8e"
  }
}
