{
  "status": "planned",
  "artifacts": [
    {
      "type": "plan",
      "path": "specs/644_redesign_learn_interactive_task_selection/plans/implementation-001.md",
      "summary": "5-phase implementation plan for redesigning /learn command to use interactive task selection"
    }
  ],
  "next_steps": "Run /implement 644 to execute the plan",
  "metadata": {
    "session_id": "sess_1768940395_9ade3c",
    "agent_type": "planner-agent",
    "duration_seconds": 180,
    "delegation_depth": 1,
    "delegation_path": ["orchestrator", "plan", "skill-planner"],
    "phase_count": 5,
    "estimated_hours": 2.5
  }
}
