{
  "status": "partial",
  "started_at": "2026-01-29T12:00:00Z",
  "completed_at": "2026-01-29T14:00:00Z",
  "artifacts": [
    {
      "path": "Theories/Bimodal/Metalogic/Algebraic/HybridCompleteness.lean",
      "type": "implementation",
      "summary": "Hybrid completeness module connecting algebraic representation to FMP path"
    },
    {
      "path": "specs/750_refactor_forward_truth_lemma_remove_sorries/summaries/implementation-summary-20260129.md",
      "type": "summary",
      "summary": "Implementation summary documenting hybrid approach and remaining gap"
    }
  ],
  "partial_progress": {
    "stage": "phase_5_complete",
    "details": "All phases completed. Created HybridCompleteness.lean with hybrid_weak_completeness theorem. Remaining sorry is in valid_implies_semantic_truth (forward truth lemma gap). Core algebraic infrastructure is sorry-free."
  },
  "completion_data": {
    "completion_summary": "Implemented hybrid completeness approach connecting algebraic representation theorem to FMP construction. Created HybridCompleteness.lean with alg_consistent_to_mcs (sorry-free) and hybrid_weak_completeness (1 sorry). The remaining sorry represents the fundamental forward truth lemma gap - connecting universal validity to truth in a specific canonical model. For practical completeness, semantic_weak_completeness remains fully sorry-free.",
    "roadmap_items": []
  },
  "metadata": {
    "session_id": "sess_1769710822_3158e8",
    "agent_type": "lean-implementation-agent",
    "delegation_depth": 1,
    "delegation_path": ["orchestrator", "implement", "skill-lean-implementation", "lean-implementation-agent"]
  }
}
