{
  "status": "researched",
  "summary": "Upward bridge is theoretically sound but requires 12-16 hours of infrastructure work (canonical MCS propagation, bounded relevance lemma, bidirectional induction). NOT on critical path - completeness proven via semantic_weak_completeness, decidability only needs cardinality bound. Recommend LOW PRIORITY or document as known limitation.",
  "artifacts": [
    {
      "type": "research",
      "path": "specs/628_prove_semantic_truth_implies_truth_at_upward_bridge/reports/research-001.md",
      "summary": "Research report analyzing the upward bridge theorem with case-by-case feasibility analysis and effort estimation"
    }
  ],
  "next_steps": "Run /plan 628 if implementation desired, or mark as LOW PRIORITY",
  "metadata": {
    "session_id": "sess_1768870570_94e25e",
    "agent_type": "lean-research-agent",
    "duration_seconds": 1800,
    "delegation_depth": 1,
    "delegation_path": ["orchestrator", "research", "lean-research-agent"],
    "findings_count": 6
  }
}
