{
  "status": "researched",
  "started_at": "2026-03-09T00:00:00Z",
  "summary": "Strategic reassessment identified 6 viable strategies. Recommended Strategy E: abandon automorphism group approach, set D=Q (rationals) directly, build Q-indexed canonical histories using DN axiom + Lindenbaum, define TaskFrame Q from histories. This bypasses all current blockers (countability FALSE, density 4 sorries, Holder/freeness/homogeneity deferred). Q has full Mathlib infrastructure. Estimated 15-25 hours. Archive DenseQuotient.lean and TranslationGroup.lean.",
  "artifacts": [
    {
      "path": "specs/956_construct_d_as_translation_group_from_syntax/reports/research-019.md",
      "type": "research",
      "summary": "Comprehensive strategic reassessment: analyzes root causes of 3 blockers, evaluates 6 strategies (A-F), recommends Strategy E (D=Q fragment-based construction), details Mathlib infrastructure available, outlines Q-indexed canonical history construction, provides concrete next steps"
    }
  ],
  "partial_progress": {
    "stage": "report_written",
    "details": "Research report research-019.md written with full strategic analysis"
  },
  "metadata": {
    "session_id": "sess_1773097577_9a8176",
    "agent_type": "lean-research-agent",
    "delegation_depth": 2,
    "delegation_path": ["orchestrator", "research", "skill-lean-research", "lean-research-agent"]
  }
}
