{
  "status": "researched",
  "artifacts": [
    {
      "path": "specs/997_wire_algebraic_base_completeness/reports/01_wire-base-completeness.md",
      "type": "research",
      "summary": "Analysis of FMCSTransfer wiring for base completeness - identifies need for Int dovetailing chain construction as prerequisite"
    }
  ],
  "metadata": {
    "session_id": "sess_1773953586_58e9a7",
    "agent_type": "lean-research-agent",
    "delegation_depth": 1,
    "delegation_path": ["orchestrator", "research", "lean-research-agent"]
  }
}
