{
  "status": "partial",
  "artifacts": [
    {
      "type": "summary",
      "path": "specs/864_recursive_seed_henkin_model/summaries/implementation-summary-20260218.md",
      "summary": "Phase 1 verified complete (from task 900), Phase 2 in progress with 2 helper lemmas added"
    },
    {
      "type": "handoff",
      "path": "specs/864_recursive_seed_henkin_model/handoffs/phase-2-handoff-20260218-1.md",
      "summary": "Handoff document for Phase 2 closure proofs"
    }
  ],
  "partial_progress": {
    "stage": "phase_2_closure_proofs",
    "details": "Added 2 helper lemmas (addFormula_hasPosition_backward, classifyFormula_eq_atomic). Documented 10-case proof structure. Sorry count unchanged at 21.",
    "phases_completed": 1,
    "phases_total": 6,
    "handoff_path": "specs/864_recursive_seed_henkin_model/handoffs/phase-2-handoff-20260218-1.md"
  },
  "metadata": {
    "session_id": "sess_1771444424_210e88",
    "agent_type": "lean-implementation-agent",
    "delegation_depth": 1,
    "delegation_path": ["orchestrator", "implement", "skill-lean-implementation", "lean-implementation-agent"],
    "sorry_count_start": 21,
    "sorry_count_end": 21,
    "helper_lemmas_added": 2
  },
  "completion_data": {
    "completion_summary": "Phase 1 verified complete from task 900. Phase 2 in progress: added 2 zero-sorry helper lemmas (addFormula_hasPosition_backward, classifyFormula_eq_atomic) and documented the 10-case proof structure for processWorkItem_preserves_closure."
  }
}
